gerador_api_segura_v3/__init__.py
gerador_api_segura_v3/__main__.py
gerador_api_segura_v3/cli.py
gerador_api_segura_v3/data/__init__.py
gerador_api_segura_v3/data/gerador_api_segura_v3.py
gerador_api_segura_v3-0.1.15.dist-info/METADATA
gerador_api_segura_v3-0.1.15.dist-info/WHEEL
gerador_api_segura_v3-0.1.15.dist-info/entry_points.txt
gerador_api_segura_v3-0.1.15.dist-info/licenses/LICENSE
gerador_api_segura_v3-0.1.15.dist-info/RECORD
