Metadata-Version: 2.4
Name: gerador-api-segura-v3
Version: 0.1.15
Summary: CLI para gerar projeto API Flask segura (Mongo/MariaDB/PostgreSQL) a partir de um template robusto.
Author: wanderson.felipe
License: MIT License
License-File: LICENSE
Classifier: Programming Language :: Python :: 3 :: Only
Requires-Python: >=3.10
